LICENSE.txt
MANIFEST.in
README.md
pyproject.toml
setup.cfg
src/pyalamake/__init__.py
src/pyalamake/arduino_shared.py
src/pyalamake/boards.json
src/pyalamake/compile_cmd_json.py
src/pyalamake/constants_version.py
src/pyalamake/gbl.py
src/pyalamake/list_param.py
src/pyalamake/makefile_variables.py
src/pyalamake/osal.py
src/pyalamake/package_cpip.py
src/pyalamake/package_opengl.py
src/pyalamake/path_handle.py
src/pyalamake/pyalamake.py
src/pyalamake/svc.py
src/pyalamake/target_arduino.py
src/pyalamake/target_arduino_core.py
src/pyalamake/target_base.py
src/pyalamake/target_base_min.py
src/pyalamake/target_c.py
src/pyalamake/target_c_cpp_base.py
src/pyalamake/target_c_cpp_lib_base.py
src/pyalamake/target_c_lib.py
src/pyalamake/target_cpp.py
src/pyalamake/target_cpp_lib.py
src/pyalamake/target_gtest.py
src/pyalamake/target_manual.py
src/pyalamake/target_swig.py
src/pyalamake.egg-info/PKG-INFO
src/pyalamake.egg-info/SOURCES.txt
src/pyalamake.egg-info/dependency_links.txt
src/pyalamake.egg-info/requires.txt
src/pyalamake.egg-info/top_level.txt