Metadata-Version: 2.4
Name: pyalamake
Version: 2.0.0
Summary: python module to generate Makefiles for arduino, GTest, /CC++, etc.
Author-email: "J. Arrizza" <cppgent0@gmail.com>
Maintainer-email: "J. Arrizza" <cppgent0@gmail.com>
License-Expression: MIT
Project-URL: Website, https://arrizza.com/pyalamake
Project-URL: Source, https://bitbucket.org/arrizza-public/pyalamake/src/master
Project-URL: Download, https://bitbucket.org/arrizza-public/pyalamake/get/master.zip
Keywords: makefile,generation,python
Classifier: Development Status :: 4 - Beta
Classifier: Environment :: Console
Classifier: Topic :: Utilities
Classifier: Intended Audience :: Developers
Classifier: Programming Language :: Python :: 3.10
Classifier: Programming Language :: Python :: 3.12
Requires-Python: >=3.9
License-File: LICENSE.txt
Requires-Dist: falcon-logger
Dynamic: license-file
